greenpass/URLs.py
greenpass/__init__.py
greenpass/api.py
greenpass/data.py
greenpass/input.py
greenpass/logic.py
greenpass/output.py
greenpass/settings.py
greenpass-4.3.1.data/scripts/greenpass
greenpass-4.3.1.dist-info/LICENSE
greenpass-4.3.1.dist-info/METADATA
greenpass-4.3.1.dist-info/WHEEL
greenpass-4.3.1.dist-info/top_level.txt
greenpass-4.3.1.dist-info/RECORD
