Metadata-Version: 2.1
Name: greenpass
Version: 4.3.1
Summary: Scriptable green pass verifier
Home-page: https://github.com/berdav/greenpass
Author: Davide Berardi
Author-email: berardi.dav@gmail.com
License: LGPLv3
Download-URL: https://github.com/berdav/greenpass/archive/refs/tags/v4.3.1.zip
Keywords: covid19,greenpass,certificates,authorization
Platform: UNKNOWN
Classifier: Development Status :: 5 - Production/Stable
Classifier: Environment :: Console
Classifier: Intended Audience :: Healthcare Industry
Classifier: License :: OSI Approved :: GNU Lesser General Public License v3 or later (LGPLv3+)
Classifier: Topic :: Utilities
Classifier: Programming Language :: Python :: 3
Classifier: Programming Language :: Python :: 3.4
Classifier: Programming Language :: Python :: 3.5
Classifier: Programming Language :: Python :: 3.6
Classifier: Programming Language :: Python :: 3.7
Classifier: Programming Language :: Python :: 3.8
Classifier: Programming Language :: Python :: 3.9
Classifier: Programming Language :: Python :: 3.10
Requires-Dist: Pillow
Requires-Dist: PyMuPDF
Requires-Dist: base45
Requires-Dist: bs4
Requires-Dist: cbor2
Requires-Dist: colorama
Requires-Dist: cose
Requires-Dist: pyOpenSSL
Requires-Dist: pyasn1
Requires-Dist: pytz
Requires-Dist: pyzbar
Requires-Dist: requests
Requires-Dist: termcolor
Requires-Dist: tzlocal
